py_cce/__init__.py
py_cce/base/__init__.py
py_cce/base/annotations.py
py_cce/base/data.py
py_cce/base/exceptions.py
py_cce/base/model.py
py_cce/base/results.py
py_cce/models/__init__.py
py_cce/models/cce_individual.py
py_cce/models/cce_mg.py
py_cce/models/cce_pooled.py
py_cce/utils/__init__.py
py_cce/utils/augmentation.py
py_cce/utils/csa.py
py_cce/utils/data.py
py_cce/utils/mc_study.py
py_cce/utils/rank_condition.py
py_cce/utils/sample.py
pycce_rc-0.6.0.dist-info/LICENSE
pycce_rc-0.6.0.dist-info/METADATA
pycce_rc-0.6.0.dist-info/WHEEL
pycce_rc-0.6.0.dist-info/RECORD
