Metadata-Version: 2.3
Name: PyCCE-RC
Version: 0.6.0
Summary: Package for handling panel data with strong cross-sectional dependence
License: GPL-3.0-or-later
Author: Merijn Huiskes
Author-email: merijnhuiskes1@gmail.com
Requires-Python: >=3.12,<4.0
Classifier: License :: OSI Approved :: GNU General Public License v3 or later (GPLv3+)
Classifier: Programming Language :: Python :: 3
Classifier: Programming Language :: Python :: 3.12
Classifier: Programming Language :: Python :: 3.13
Requires-Dist: numpy (>=2.2.3,<3.0.0)
Requires-Dist: pandas (>=2.3.0,<3.0.0)
